realdebrid/__init__.py
realdebrid-0.0.2.dist-info/METADATA
realdebrid-0.0.2.dist-info/WHEEL
realdebrid-0.0.2.dist-info/top_level.txt
realdebrid-0.0.2.dist-info/RECORD
